slurmy/__init__.py
slurmy/backends/__init__.py
slurmy/backends/base.py
slurmy/backends/defs.py
slurmy/backends/htcondor.py
slurmy/backends/slurm.py
slurmy/backends/utils.py
slurmy/test/__init__.py
slurmy/test/__main__.py
slurmy/test/jobconfig.py
slurmy/test/submission.py
slurmy/tools/__init__.py
slurmy/tools/defs.py
slurmy/tools/job.py
slurmy/tools/jobcontainer.py
slurmy/tools/jobhandler.py
slurmy/tools/listener.py
slurmy/tools/namegenerator.py
slurmy/tools/options.py
slurmy/tools/parser.py
slurmy/tools/printer.py
slurmy/tools/profiler.py
slurmy/tools/tags.py
slurmy/tools/utils.py
slurmy/tools/wrapper.py
slurmy-1.3.1.data/scripts/slurmy
slurmy-1.3.1.data/scripts/slurmy2
slurmy-1.3.1.dist-info/LICENSE
slurmy-1.3.1.dist-info/METADATA
slurmy-1.3.1.dist-info/WHEEL
slurmy-1.3.1.dist-info/top_level.txt
slurmy-1.3.1.dist-info/RECORD
