Metadata-Version: 2.1
Name: slurmy
Version: 1.3.1
Summary: Manager of batch jobs accross different backends.
Home-page: https://github.com/Thomas-Maier/slurmy
Author: Thomas Maier
Author-email: thomas.maier1989@gmail.com
License: UNKNOWN
Platform: UNKNOWN
Classifier: Programming Language :: Python :: 3
Classifier: License :: OSI Approved :: GNU General Public License v3 (GPLv3)
Classifier: Operating System :: POSIX :: Linux
Requires-Dist: tqdm
